cdktf_cdktf_provider_upcloud/__init__.py
cdktf_cdktf_provider_upcloud/py.typed
cdktf_cdktf_provider_upcloud/_jsii/__init__.py
cdktf_cdktf_provider_upcloud/_jsii/provider-upcloud@15.8.1.jsii.tgz
cdktf_cdktf_provider_upcloud/data_upcloud_hosts/__init__.py
cdktf_cdktf_provider_upcloud/data_upcloud_ip_addresses/__init__.py
cdktf_cdktf_provider_upcloud/data_upcloud_kubernetes_cluster/__init__.py
cdktf_cdktf_provider_upcloud/data_upcloud_load_balancer_dns_challenge_domain/__init__.py
cdktf_cdktf_provider_upcloud/data_upcloud_managed_database_mysql_sessions/__init__.py
cdktf_cdktf_provider_upcloud/data_upcloud_managed_database_opensearch_indices/__init__.py
cdktf_cdktf_provider_upcloud/data_upcloud_managed_database_postgresql_sessions/__init__.py
cdktf_cdktf_provider_upcloud/data_upcloud_managed_database_valkey_sessions/__init__.py
cdktf_cdktf_provider_upcloud/data_upcloud_managed_object_storage_policies/__init__.py
cdktf_cdktf_provider_upcloud/data_upcloud_managed_object_storage_regions/__init__.py
cdktf_cdktf_provider_upcloud/data_upcloud_networks/__init__.py
cdktf_cdktf_provider_upcloud/data_upcloud_storage/__init__.py
cdktf_cdktf_provider_upcloud/data_upcloud_tags/__init__.py
cdktf_cdktf_provider_upcloud/data_upcloud_zone/__init__.py
cdktf_cdktf_provider_upcloud/data_upcloud_zones/__init__.py
cdktf_cdktf_provider_upcloud/file_storage/__init__.py
cdktf_cdktf_provider_upcloud/firewall_rules/__init__.py
cdktf_cdktf_provider_upcloud/floating_ip_address/__init__.py
cdktf_cdktf_provider_upcloud/gateway/__init__.py
cdktf_cdktf_provider_upcloud/gateway_connection/__init__.py
cdktf_cdktf_provider_upcloud/gateway_connection_tunnel/__init__.py
cdktf_cdktf_provider_upcloud/kubernetes_cluster/__init__.py
cdktf_cdktf_provider_upcloud/kubernetes_node_group/__init__.py
cdktf_cdktf_provider_upcloud/loadbalancer/__init__.py
cdktf_cdktf_provider_upcloud/loadbalancer_backend/__init__.py
cdktf_cdktf_provider_upcloud/loadbalancer_backend_tls_config/__init__.py
cdktf_cdktf_provider_upcloud-15.8.1.dist-info/LICENSE
cdktf_cdktf_provider_upcloud-15.8.1.dist-info/METADATA
cdktf_cdktf_provider_upcloud-15.8.1.dist-info/WHEEL
cdktf_cdktf_provider_upcloud-15.8.1.dist-info/top_level.txt
cdktf_cdktf_provider_upcloud-15.8.1.dist-info/RECORD
